[
  {
    "label": "Boshqaruv",
    "icon": "pi pi-user",
    "type": "link",
    "route": "dashboard",
    "permissions": []
  },
  {
    "label": "Ombor",
    "icon": "pi pi-warehouse",
    "type": "link",
    "route": "warehouse",
    "permissions": []
  },
  {
    "label": "Katalog",
    "icon": "pi pi-address-book",
    "type": "link",
    "route": "catalog",
    "permissions": []
  },
  {
    "label": "Kassa",
    "icon": "pi pi-calculator",
    "type": "link",
    "route": "cashbox",
    "permissions": []
  },
  {
    "label": "Hisobot",
    "icon": "pi pi-chart-bar",
    "type": "link",
    "route": "analytics",
    "permissions": []
  }
]

